[
  {
    "trial_id": 0,
    "hyperparameters": {
      "batch_size": 128,
      "learning_rate": 0.0005,
      "n_layers": 2,
      "units": 64,
      "dropout": 0.0,
      "filters": 128,
      "kernel_size": 3
    },
    "decision_threshold": 0.6381813883781433,
    "threshold_source": "validation",
    "threshold_policy": "optimal_f2",
    "threshold_metric": "f2",
    "threshold_warning": null,
    "val_precision": 0.9843527013251784,
    "val_recall": 0.9973662466432556,
    "val_f1": 0.9908167453314181,
    "val_pr_auc": 0.9997011937467879,
    "epochs": 5,
    "batch_size": 128,
    "requested_batch_size": 128
  },
  {
    "trial_id": 1,
    "hyperparameters": {
      "batch_size": 256,
      "learning_rate": 0.001,
      "n_layers": 1,
      "units": 128,
      "dropout": 0.2,
      "filters": 128,
      "kernel_size": 5
    },
    "decision_threshold": 0.6584563851356506,
    "threshold_source": "validation",
    "threshold_policy": "optimal_f2",
    "threshold_metric": "f2",
    "threshold_warning": null,
    "val_precision": 0.9853023730543506,
    "val_recall": 0.9970563933071679,
    "val_f1": 0.9911445365640802,
    "val_pr_auc": 0.9996886971275648,
    "epochs": 5,
    "batch_size": 256,
    "requested_batch_size": 256
  },
  {
    "trial_id": 2,
    "hyperparameters": {
      "batch_size": 256,
      "learning_rate": 0.0005,
      "n_layers": 2,
      "units": 64,
      "dropout": 0.2,
      "filters": 64,
      "kernel_size": 5
    },
    "decision_threshold": 0.6483562588691711,
    "threshold_source": "validation",
    "threshold_policy": "optimal_f2",
    "threshold_metric": "f2",
    "threshold_warning": null,
    "val_precision": 0.9856530174614521,
    "val_recall": 0.9969531088618054,
    "val_f1": 0.9912708600770218,
    "val_pr_auc": 0.9997109129633487,
    "epochs": 5,
    "batch_size": 256,
    "requested_batch_size": 256
  }
]